iso639/__init__.py
iso639/datafile.py
iso639/exceptions.py
iso639/iso639.py
iso639/data/iso-639.json
iso639/data/iso-639_deprecated.json
iso639/data/iso-639_langs.json
iso639/data/iso-639_macro.json
iso639/data/iso-639_other_names.json
iso639/data/iso-639_ref_name.json
iso639/data/iso-639_scope.json
iso639/data/iso-639_type.json
iso639_lang-2.5.0.dist-info/LICENSE.txt
iso639_lang-2.5.0.dist-info/METADATA
iso639_lang-2.5.0.dist-info/WHEEL
iso639_lang-2.5.0.dist-info/top_level.txt
iso639_lang-2.5.0.dist-info/RECORD
