Metadata-Version: 2.1
Name: iso639-lang
Version: 2.5.0
Summary: A fast, simple ISO 639 library.
Author-email: Laurent Beaudoux <lbeaudoux@gmail.com>
Project-URL: Homepage, https://github.com/LBeaudoux/iso639
Keywords: ISO 639,ISO 639-1,ISO 639-2,ISO 639-3,ISO 639-5,language code
Classifier: Development Status :: 5 - Production/Stable
Classifier: License :: OSI Approved :: MIT License
Classifier: Operating System :: OS Independent
Classifier: Programming Language :: Python :: 3
Classifier: Programming Language :: Python :: 3.8
Classifier: Programming Language :: Python :: 3.9
Classifier: Programming Language :: Python :: 3.10
Classifier: Programming Language :: Python :: 3.11
Classifier: Programming Language :: Python :: 3.12
Classifier: Programming Language :: Python :: 3.13
Classifier: Topic :: Software Development :: Internationalization
Classifier: Topic :: Software Development :: Localization
Classifier: Topic :: Text Processing :: Linguistic
Requires-Python: >=3.8
License-File: LICENSE.txt
Requires-Dist: importlib-resources ; python_version < "3.9"
